pymixture/__init__.py
pymixture-0.0.0.dist-info/licenses/LICENSE
pymixture-0.0.0.dist-info/METADATA
pymixture-0.0.0.dist-info/WHEEL
pymixture-0.0.0.dist-info/top_level.txt
pymixture-0.0.0.dist-info/RECORD
