Metadata-Version: 2.4
Name: pymixture
Version: 0.0.0
Summary: A package for mixture models
Author-email: Omri Tomer <omritomer1990@gmail.com>
License: BSD-3-Clause
Project-URL: Source, https://github.com/omritomer/pymixture
Classifier: Programming Language :: Python :: 3
Classifier: License :: OSI Approved :: BSD License
Classifier: Operating System :: OS Independent
Requires-Python: >=3.9
License-File: LICENSE
Dynamic: license-file
